LICENSE.txt
setup.py
RyzenTest.egg-info/PKG-INFO
RyzenTest.egg-info/SOURCES.txt
RyzenTest.egg-info/dependency_links.txt
RyzenTest.egg-info/top_level.txt
code/__init__.py